openlabcluster/__init__.py
openlabcluster/__main__.py
openlabcluster/version.py
openlabcluster/training_utils/__init__.py
openlabcluster/training_utils/itertrain.py
openlabcluster/training_utils/training.py
openlabcluster/user_interface/__init__.py
openlabcluster/user_interface/active_labeling.py
openlabcluster/user_interface/active_selection.py
openlabcluster/user_interface/classify_behavior.py
openlabcluster/user_interface/cluster_map.py
openlabcluster/user_interface/extract_hidden.py
openlabcluster/user_interface/init_proj.py
openlabcluster/user_interface/plot_hidden.py
openlabcluster/user_interface/plotting_utils.py
openlabcluster/user_interface/run_gui.py
openlabcluster/user_interface/run_gui_pythonw.py
openlabcluster-0.0.37.dist-info/LICENSE
openlabcluster-0.0.37.dist-info/METADATA
openlabcluster-0.0.37.dist-info/WHEEL
openlabcluster-0.0.37.dist-info/entry_points.txt
openlabcluster-0.0.37.dist-info/top_level.txt
openlabcluster-0.0.37.dist-info/RECORD
