Metadata-Version: 2.1
Name: openlabcluster
Version: 0.0.37
Summary: OpenLabCluster
Home-page: https://github.com/shlizee/OpenLabCluster
Author: Jingyuan Li
Author-email: jingyli6@uw.edu
Keywords: python,first package
Classifier: Development Status :: 3 - Alpha
Classifier: Intended Audience :: Education
Classifier: Programming Language :: Python :: 2
Classifier: Programming Language :: Python :: 3
Classifier: Operating System :: MacOS :: MacOS X
Classifier: Operating System :: Microsoft :: Windows
License-File: LICENSE
Requires-Dist: deeplabcut (==2.2.0.6)
Requires-Dist: easydict (==1.9)
Requires-Dist: h5py (==3.1.0)
Requires-Dist: matplotlib (==3.1.3)
Requires-Dist: numpy (==1.19.5)
Requires-Dist: opencv-python (==4.5.1.48)
Requires-Dist: pandas (==1.1.5)
Requires-Dist: ruamel.yaml (==0.16.13)
Requires-Dist: ruamel.yaml.clib (==0.2.6)
Requires-Dist: scikit-image (==0.17.2)
Requires-Dist: scikit-learn (==0.24.1)
Requires-Dist: scipy (==1.6.1)
Requires-Dist: torch (==1.8.0)
Requires-Dist: torchvision (==0.9.0)
Requires-Dist: umap-learn (==0.5.1)
Requires-Dist: openpyxl
Provides-Extra: user_interface
Requires-Dist: wxpython (<4.1) ; extra == 'user_interface'
